{"b2b": [{"inv": [{"dt": "07-07-2020", "val": 985, "rev": "N", "itcavl": "Y", "diffprcnt": 1, "pos": "33", "typ": "R", "inum": "8571", "rsn": "", "items": [{"sgst": 52.77, "rt": 12, "num": 1, "txval": 879.5, "cgst": 52.77, "cess": 0}]}], "trdnm": "SARASWATHI AGENCIES", "supfildt": "23-08-2020", "supprd": "072020", "ctin": "33AEEPR4761D2ZM"}, {"inv": [{"dt": "12-08-2020", "val": 1015, "rev": "N", "itcavl": "Y", "diffprcnt": 1, "pos": "33", "typ": "R", "inum": "HO-004203", "rsn": "", "items": [{"sgst": 6.16, "rt": 12, "num": 1201, "txval": 102.68, "cgst": 6.16, "cess": 0}, {"sgst": 68.64, "rt": 18, "num": 1801, "txval": 762.71, "cgst": 68.64, "cess": 0}]}], "trdnm": "M.P.M.MUTHU GENERAL STORES", "supfildt": "09-09-2020", "supprd": "082020", "ctin": "33AAAFM8415D1ZQ"}, {"inv": [{"dt": "28-08-2020", "val": 387, "rev": "N", "itcavl": "Y", "diffprcnt": 1, "pos": "33", "typ": "R", "inum": "16202", "rsn": "", "items": [{"sgst": 20.72, "rt": 12, "num": 1, "txval": 345.28, "cgst": 20.72, "cess": 0}]}], "trdnm": "SARASWATHI AGENCIES", "supfildt": "08-09-2020", "supprd": "082020", "ctin": "33AEEPR4761D2ZM"}, {"inv": [{"dt": "22-07-2020", "val": 750, "rev": "N", "itcavl": "Y", "diffprcnt": 1, "pos": "33", "typ": "R", "inum": "HO-003246", "rsn": "", "items": [{"sgst": 57.2, "rt": 18, "num": 1801, "txval": 635.59, "cgst": 57.2, "cess": 0}]}, {"dt": "31-07-2020", "val": 750, "rev": "N", "itcavl": "Y", "diffprcnt": 1, "pos": "33", "typ": "R", "inum": "HO-003660", "rsn": "", "items": [{"sgst": 57.2, "rt": 18, "num": 1801, "txval": 635.59, "cgst": 57.2, "cess": 0}]}], "trdnm": "M.P.M.MUTHU GENERAL STORES", "supfildt": "17-08-2020", "supprd": "072020", "ctin": "33AAAFM8415D1ZQ"}, {"inv": [{"dt": "15-06-2020", "val": 700, "rev": "N", "itcavl": "Y", "diffprcnt": 1, "pos": "33", "typ": "R", "inum": "APS/1002/20-21", "rsn": "", "items": [{"sgst": 53.39, "rt": 18, "num": 1, "txval": 593.22, "cgst": 53.39, "cess": 0}]}, {"dt": "18-06-2020", "val": 900, "rev": "N", "itcavl": "Y", "diffprcnt": 1, "pos": "33", "typ": "R", "inum": "APS/1054/20-21", "rsn": "", "items": [{"sgst": 68.64, "rt": 18, "num": 1, "txval": 762.71, "cgst": 68.64, "cess": 0}]}, {"dt": "03-06-2020", "val": 700, "rev": "N", "itcavl": "Y", "diffprcnt": 1, "pos": "33", "typ": "R", "inum": "APS/836/20-21", "rsn": "", "items": [{"sgst": 53.39, "rt": 18, "num": 1, "txval": 593.22, "cgst": 53.39, "cess": 0}]}], "trdnm": "ANNAMALAI PAPER STORE", "supfildt": "04-09-2020", "supprd": "062020", "ctin": "33AQJPM1275C2Z4"}, {"inv": [{"dt": "03-08-2020", "val": 649418.53, "rev": "N", "itcavl": "Y", "diffprcnt": 1, "pos": "33", "typ": "R", "inum": "9033041808", "rsn": "", "items": [{"sgst": 49019.77, "rt": 18, "num": 1, "txval": 544664.33, "cgst": 49019.77}, {"sgst": 359.71, "rt": 12, "num": 2, "txval": 5995.24, "cgst": 359.71}]}, {"dt": "03-08-2020", "val": 82755.7, "rev": "N", "itcavl": "Y", "diffprcnt": 1, "pos": "33", "typ": "R", "inum": "9033041809", "rsn": "", "items": [{"sgst": 1771.64, "rt": 5, "num": 1, "txval": 70865.12, "cgst": 1771.64}, {"sgst": 118.47, "rt": 12, "num": 2, "txval": 1974.44, "cgst": 118.47}, {"sgst": 467.99, "rt": 18, "num": 3, "txval": 5199.94, "cgst": 467.99}]}, {"dt": "06-08-2020", "val": 485319.33, "rev": "N", "itcavl": "Y", "diffprcnt": 1, "pos": "33", "typ": "R", "inum": "9033042592", "rsn": "", "items": [{"sgst": 36385.58, "rt": 18, "num": 1, "txval": 404283.96, "cgst": 36385.58}, {"sgst": 442.73, "rt": 12, "num": 2, "txval": 7378.75, "cgst": 442.73}]}, {"dt": "06-08-2020", "val": 145448.85, "rev": "N", "itcavl": "Y", "diffprcnt": 1, "pos": "33", "typ": "R", "inum": "9033042593", "rsn": "", "items": [{"sgst": 2946.63, "rt": 5, "num": 1, "txval": 117864.83, "cgst": 2946.63}, {"sgst": 699.52, "rt": 12, "num": 2, "txval": 11658.59, "cgst": 699.52}, {"sgst": 658.46, "rt": 18, "num": 3, "txval": 7316.21, "cgst": 658.46}]}, {"dt": "06-08-2020", "val": 189767.92, "rev": "N", "itcavl": "Y", "diffprcnt": 1, "pos": "33", "typ": "R", "inum": "9033042595", "rsn": "", "items": [{"sgst": 2451.87, "rt": 5, "num": 1, "txval": 98074.71, "cgst": 2451.87}, {"sgst": 6619.54, "rt": 18, "num": 2, "txval": 73550.39, "cgst": 6619.54}]}, {"dt": "06-08-2020", "val": 255932.58, "rev": "N", "itcavl": "Y", "diffprcnt": 1, "pos": "33", "typ": "R", "inum": "9033042596", "rsn": "", "items": [{"sgst": 19520.27, "rt": 18, "num": 1, "txval": 216892.04, "cgst": 19520.27}]}, {"dt": "07-08-2020", "val": 124100.47, "rev": "N", "itcavl": "Y", "diffprcnt": 1, "pos": "33", "typ": "R", "inum": "9033043219", "rsn": "", "items": [{"sgst": 9465.29, "rt": 18, "num": 1, "txval": 105169.89, "cgst": 9465.29}]}, {"dt": "07-08-2020", "val": 427374.64, "rev": "N", "itcavl": "Y", "diffprcnt": 1, "pos": "33", "typ": "R", "inum": "9033043222", "rsn": "", "items": [{"sgst": 32596.37, "rt": 18, "num": 1, "txval": 362181.9, "cgst": 32596.37}]}, {"dt": "08-08-2020", "val": 767341.79, "rev": "N", "itcavl": "Y", "diffprcnt": 1, "pos": "33", "typ": "R", "inum": "9033043772", "rsn": "", "items": [{"sgst": 58013.93, "rt": 18, "num": 1, "txval": 644599.27, "cgst": 58013.93}, {"sgst": 359.71, "rt": 12, "num": 2, "txval": 5995.24, "cgst": 359.71}]}, {"dt": "08-08-2020", "val": 230943.24, "rev": "N", "itcavl": "Y", "diffprcnt": 1, "pos": "33", "typ": "R", "inum": "9033043773", "rsn": "", "items": [{"sgst": 4453.59, "rt": 5, "num": 1, "txval": 178143.37, "cgst": 4453.59}, {"sgst": 1028.87, "rt": 12, "num": 2, "txval": 17147.85, "cgst": 1028.87}, {"sgst": 1882.91, "rt": 18, "num": 3, "txval": 20921.28, "cgst": 1882.91}]}, {"dt": "08-08-2020", "val": 73358.71, "rev": "N", "itcavl": "Y", "diffprcnt": 1, "pos": "33", "typ": "R", "inum": "9033043777", "rsn": "", "items": [{"sgst": 1746.64, "rt": 5, "num": 1, "txval": 69865.43, "cgst": 1746.64}]}, {"dt": "11-08-2020", "val": 1127637.41, "rev": "N", "itcavl": "Y", "diffprcnt": 1, "pos": "33", "typ": "R", "inum": "9033044396", "rsn": "", "items": [{"sgst": 85494.11, "rt": 18, "num": 1, "txval": 949934.53, "cgst": 85494.11}, {"sgst": 359.71, "rt": 12, "num": 2, "txval": 5995.24, "cgst": 359.71}]}, {"dt": "11-08-2020", "val": 300593.8, "rev": "N", "itcavl": "Y", "diffprcnt": 1, "pos": "33", "typ": "R", "inum": "9033044397", "rsn": "", "items": [{"sgst": 780.38, "rt": 12, "num": 1, "txval": 13006.24, "cgst": 780.38}, {"sgst": 4481.89, "rt": 5, "num": 2, "txval": 179275.22, "cgst": 4481.89}, {"sgst": 7458.39, "rt": 18, "num": 3, "txval": 82871.02, "cgst": 7458.39}]}, {"dt": "11-08-2020", "val": 130478.12, "rev": "N", "itcavl": "Y", "diffprcnt": 1, "pos": "33", "typ": "R", "inum": "9033044546", "rsn": "", "items": [{"sgst": 9951.71, "rt": 18, "num": 1, "txval": 110574.7, "cgst": 9951.71}]}, {"dt": "13-08-2020", "val": 531541.89, "rev": "N", "itcavl": "Y", "diffprcnt": 1, "pos": "33", "typ": "R", "inum": "9033045345", "rsn": "", "items": [{"sgst": 40541.32, "rt": 18, "num": 1, "txval": 450459.25, "cgst": 40541.32}]}, {"dt": "13-08-2020", "val": 310313.46, "rev": "N", "itcavl": "Y", "diffprcnt": 1, "pos": "33", "typ": "R", "inum": "9033045346", "rsn": "", "items": [{"sgst": 6302.92, "rt": 18, "num": 1, "txval": 70032.51, "cgst": 6302.92}, {"sgst": 4528.27, "rt": 5, "num": 2, "txval": 181130.58, "cgst": 4528.27}, {"sgst": 2008.28, "rt": 12, "num": 3, "txval": 33471.43, "cgst": 2008.28}]}, {"dt": "16-08-2020", "val": 474517.66, "rev": "N", "itcavl": "Y", "diffprcnt": 1, "pos": "33", "typ": "R", "inum": "9033046720", "rsn": "", "items": [{"sgst": 3308.71, "rt": 5, "num": 1, "txval": 132348.22, "cgst": 3308.71}, {"sgst": 2933.74, "rt": 12, "num": 2, "txval": 48895.55, "cgst": 2933.74}, {"sgst": 21416.11, "rt": 18, "num": 3, "txval": 237956.77, "cgst": 21416.11}]}, {"dt": "16-08-2020", "val": 450159.8, "rev": "N", "itcavl": "Y", "diffprcnt": 1, "pos": "33", "typ": "R", "inum": "9033046721", "rsn": "", "items": [{"sgst": 34334.26, "rt": 18, "num": 1, "txval": 381491.28, "cgst": 34334.26}]}, {"dt": "16-08-2020", "val": 17671.9, "rev": "N", "itcavl": "Y", "diffprcnt": 1, "pos": "33", "typ": "R", "inum": "9033046725", "rsn": "", "items": [{"sgst": 1347.86, "rt": 18, "num": 1, "txval": 14976.18, "cgst": 1347.86}]}, {"dt": "16-08-2020", "val": 180365.82, "rev": "N", "itcavl": "Y", "diffprcnt": 1, "pos": "33", "typ": "R", "inum": "9033046726", "rsn": "", "items": [{"sgst": 1572.69, "rt": 5, "num": 1, "txval": 62907.46, "cgst": 1572.69}, {"sgst": 8718.79, "rt": 18, "num": 2, "txval": 96875.4, "cgst": 8718.79}]}, {"dt": "17-08-2020", "val": 869677.8, "rev": "N", "itcavl": "Y", "diffprcnt": 1, "pos": "33", "typ": "R", "inum": "9033047143", "rsn": "", "items": [{"sgst": 66331.38, "rt": 18, "num": 1, "txval": 737015.04, "cgst": 66331.38}]}, {"dt": "17-08-2020", "val": 364643.25, "rev": "N", "itcavl": "Y", "diffprcnt": 1, "pos": "33", "typ": "R", "inum": "9033047144", "rsn": "", "items": [{"sgst": 1393.67, "rt": 12, "num": 1, "txval": 23227.87, "cgst": 1393.67}, {"sgst": 5968.17, "rt": 5, "num": 2, "txval": 238726.19, "cgst": 5968.17}, {"sgst": 6709.23, "rt": 18, "num": 3, "txval": 74547.05, "cgst": 6709.23}]}, {"dt": "18-08-2020", "val": 950146.49, "rev": "N", "itcavl": "Y", "diffprcnt": 1, "pos": "33", "typ": "R", "inum": "9033047692", "rsn": "", "items": [{"sgst": 72468.82, "rt": 18, "num": 1, "txval": 805208.85, "cgst": 72468.82}]}, {"dt": "18-08-2020", "val": 377759.55, "rev": "N", "itcavl": "Y", "diffprcnt": 1, "pos": "33", "typ": "R", "inum": "9033047693", "rsn": "", "items": [{"sgst": 270.78, "rt": 12, "num": 1, "txval": 4513, "cgst": 270.78}, {"sgst": 8591.73, "rt": 5, "num": 2, "txval": 343668.94, "cgst": 8591.73}, {"sgst": 904.01, "rt": 18, "num": 3, "txval": 10044.57, "cgst": 904.01}]}, {"dt": "19-08-2020", "val": 625616.35, "rev": "N", "itcavl": "Y", "diffprcnt": 1, "pos": "33", "typ": "R", "inum": "9033048217", "rsn": "", "items": [{"sgst": 14895.63, "rt": 5, "num": 1, "txval": 595825.09, "cgst": 14895.63}]}, {"dt": "19-08-2020", "val": 611584.48, "rev": "N", "itcavl": "Y", "diffprcnt": 1, "pos": "33", "typ": "R", "inum": "9033048260", "rsn": "", "items": [{"sgst": 46015.93, "rt": 18, "num": 1, "txval": 511288.4, "cgst": 46015.93}, {"sgst": 442.73, "rt": 12, "num": 2, "txval": 7378.76, "cgst": 442.73}]}, {"dt": "19-08-2020", "val": 344936.77, "rev": "N", "itcavl": "Y", "diffprcnt": 1, "pos": "33", "typ": "R", "inum": "9033048261", "rsn": "", "items": [{"sgst": 1326.7, "rt": 18, "num": 1, "txval": 14741.25, "cgst": 1326.7}, {"sgst": 7798.62, "rt": 5, "num": 2, "txval": 311944.88, "cgst": 7798.62}]}, {"dt": "19-08-2020", "val": 519625.91, "rev": "N", "itcavl": "Y", "diffprcnt": 1, "pos": "33", "typ": "R", "inum": "9033048263", "rsn": "", "items": [{"sgst": 9569, "rt": 5, "num": 1, "txval": 382759.61, "cgst": 9569}, {"sgst": 8979.28, "rt": 18, "num": 2, "txval": 99769.74, "cgst": 8979.28}]}, {"dt": "20-08-2020", "val": 373800.9, "rev": "N", "itcavl": "Y", "diffprcnt": 1, "pos": "33", "typ": "R", "inum": "9033048618", "rsn": "", "items": [{"sgst": 28510.25, "rt": 18, "num": 1, "txval": 316780.4, "cgst": 28510.25}]}, {"dt": "20-08-2020", "val": 290546.15, "rev": "N", "itcavl": "Y", "diffprcnt": 1, "pos": "33", "typ": "R", "inum": "9033048619", "rsn": "", "items": [{"sgst": 6865.1, "rt": 5, "num": 1, "txval": 274604.57, "cgst": 6865.1}, {"sgst": 118.47, "rt": 12, "num": 2, "txval": 1974.44, "cgst": 118.47}]}, {"dt": "21-08-2020", "val": 230884.36, "rev": "N", "itcavl": "Y", "diffprcnt": 1, "pos": "33", "typ": "R", "inum": "9033048986", "rsn": "", "items": [{"sgst": 17609.82, "rt": 18, "num": 1, "txval": 195664.72, "cgst": 17609.82}]}, {"dt": "21-08-2020", "val": 22737.32, "rev": "N", "itcavl": "Y", "diffprcnt": 1, "pos": "33", "typ": "R", "inum": "9033048987", "rsn": "", "items": [{"sgst": 491.72, "rt": 5, "num": 1, "txval": 19668.86, "cgst": 491.72}, {"sgst": 111.7, "rt": 12, "num": 2, "txval": 1861.62, "cgst": 111.7}]}, {"dt": "21-08-2020", "val": 171630.76, "rev": "N", "itcavl": "Y", "diffprcnt": 1, "pos": "33", "typ": "R", "inum": "9033048990", "rsn": "", "items": [{"sgst": 4086.45, "rt": 5, "num": 1, "txval": 163457.86, "cgst": 4086.45}]}, {"dt": "25-08-2020", "val": 609033.73, "rev": "N", "itcavl": "Y", "diffprcnt": 1, "pos": "33", "typ": "R", "inum": "9033049869", "rsn": "", "items": [{"sgst": 13363.48, "rt": 5, "num": 1, "txval": 534537.95, "cgst": 13363.48}, {"sgst": 2173.77, "rt": 12, "num": 2, "txval": 36229.39, "cgst": 2173.77}, {"sgst": 548.53, "rt": 18, "num": 3, "txval": 6094.83, "cgst": 548.53}]}, {"dt": "25-08-2020", "val": 398544.84, "rev": "N", "itcavl": "Y", "diffprcnt": 1, "pos": "33", "typ": "R", "inum": "9033049870", "rsn": "", "items": [{"sgst": 29767.16, "rt": 18, "num": 1, "txval": 330746.31, "cgst": 29767.16}, {"sgst": 442.73, "rt": 12, "num": 2, "txval": 7378.75, "cgst": 442.73}]}, {"dt": "25-08-2020", "val": 503831.64, "rev": "N", "itcavl": "Y", "diffprcnt": 1, "pos": "33", "typ": "R", "inum": "9033050042", "rsn": "", "items": [{"sgst": 10272.46, "rt": 5, "num": 1, "txval": 410897.98, "cgst": 10272.46}, {"sgst": 3492.69, "rt": 12, "num": 2, "txval": 58211.47, "cgst": 3492.69}, {"sgst": 548.53, "rt": 18, "num": 3, "txval": 6094.83, "cgst": 548.53}]}, {"dt": "25-08-2020", "val": 374424.98, "rev": "N", "itcavl": "Y", "diffprcnt": 1, "pos": "33", "typ": "R", "inum": "9033050043", "rsn": "", "items": [{"sgst": 27927.53, "rt": 18, "num": 1, "txval": 310305.71, "cgst": 27927.53}, {"sgst": 442.73, "rt": 12, "num": 2, "txval": 7378.75, "cgst": 442.73}]}, {"dt": "25-08-2020", "val": 229480.88, "rev": "N", "itcavl": "Y", "diffprcnt": 1, "pos": "33", "typ": "R", "inum": "9033050044", "rsn": "", "items": [{"sgst": 17502.79, "rt": 18, "num": 1, "txval": 194475.3, "cgst": 17502.79}]}, {"dt": "25-08-2020", "val": 59317.55, "rev": "N", "itcavl": "Y", "diffprcnt": 1, "pos": "33", "typ": "R", "inum": "9033050045", "rsn": "", "items": [{"sgst": 1340.57, "rt": 5, "num": 1, "txval": 53622.9, "cgst": 1340.57}, {"sgst": 229.84, "rt": 18, "num": 2, "txval": 2553.83, "cgst": 229.84}]}, {"dt": "26-08-2020", "val": 615660.41, "rev": "N", "itcavl": "Y", "diffprcnt": 1, "pos": "33", "typ": "R", "inum": "9033050557", "rsn": "", "items": [{"sgst": 14306.94, "rt": 5, "num": 1, "txval": 572277.22, "cgst": 14306.94}, {"sgst": 692.76, "rt": 18, "num": 2, "txval": 7697.41, "cgst": 692.76}, {"sgst": 304.63, "rt": 12, "num": 3, "txval": 5077.12, "cgst": 304.63}]}, {"dt": "26-08-2020", "val": 331984.62, "rev": "N", "itcavl": "Y", "diffprcnt": 1, "pos": "33", "typ": "R", "inum": "9033050558", "rsn": "", "items": [{"sgst": 24690.57, "rt": 18, "num": 1, "txval": 274339.27, "cgst": 24690.57}, {"sgst": 442.73, "rt": 12, "num": 2, "txval": 7378.75, "cgst": 442.73}]}, {"dt": "26-08-2020", "val": 1943.9, "rev": "N", "itcavl": "Y", "diffprcnt": 1, "pos": "33", "typ": "R", "inum": "9033050561", "rsn": "", "items": [{"sgst": 148.26, "rt": 18, "num": 1, "txval": 1647.38, "cgst": 148.26}]}, {"dt": "28-08-2020", "val": 470750.89, "rev": "N", "itcavl": "Y", "diffprcnt": 1, "pos": "33", "typ": "R", "inum": "9033051237", "rsn": "", "items": [{"sgst": 35904.72, "rt": 18, "num": 1, "txval": 398941.45, "cgst": 35904.72}]}, {"dt": "28-08-2020", "val": 45971.72, "rev": "N", "itcavl": "Y", "diffprcnt": 1, "pos": "33", "typ": "R", "inum": "9033051238", "rsn": "", "items": [{"sgst": 1447.23, "rt": 12, "num": 1, "txval": 24120.57, "cgst": 1447.23}, {"sgst": 380.93, "rt": 18, "num": 2, "txval": 4232.52, "cgst": 380.93}, {"sgst": 332.44, "rt": 5, "num": 3, "txval": 13297.43, "cgst": 332.44}]}, {"dt": "31-08-2020", "val": 386141.63, "rev": "N", "itcavl": "Y", "diffprcnt": 1, "pos": "33", "typ": "R", "inum": "9033052595", "rsn": "", "items": [{"sgst": 118.47, "rt": 12, "num": 1, "txval": 1974.44, "cgst": 118.47}, {"sgst": 8480.56, "rt": 5, "num": 2, "txval": 339222.19, "cgst": 8480.56}, {"sgst": 2116.29, "rt": 18, "num": 3, "txval": 23514.36, "cgst": 2116.29}]}, {"dt": "31-08-2020", "val": 593672.89, "rev": "N", "itcavl": "Y", "diffprcnt": 1, "pos": "33", "typ": "R", "inum": "9033052596", "rsn": "", "items": [{"sgst": 45280.11, "rt": 18, "num": 1, "txval": 503112.67, "cgst": 45280.11}]}, {"dt": "31-08-2020", "val": 263156.11, "rev": "N", "itcavl": "Y", "diffprcnt": 1, "pos": "33", "typ": "R", "inum": "9033052597", "rsn": "", "items": [{"sgst": 6265.62, "rt": 5, "num": 1, "txval": 250624.87, "cgst": 6265.62}]}], "trdnm": "HINDUSTAN UNILEVER LIMITED", "supfildt": "10-09-2020", "supprd": "082020", "ctin": "33AAACH1004N1Z1"}, {"inv": [{"dt": "26-05-2020", "val": 950, "rev": "N", "itcavl": "Y", "diffprcnt": 1, "pos": "33", "typ": "R", "inum": "APS/547/20-21", "rsn": "", "items": [{"sgst": 72.46, "rt": 18, "num": 1, "txval": 805.08, "cgst": 72.46, "cess": 0}]}], "trdnm": "ANNAMALAI PAPER STORE", "supfildt": "04-09-2020", "supprd": "052020", "ctin": "33AQJPM1275C2Z4"}], "cdnr": [{"trdnm": "HINDUSTAN UNILEVER LIMITED", "supfildt": "10-09-2020", "supprd": "082020", "nt": [{"dt": "07-08-2020", "val": 644.63, "diffprcnt": 1, "itcavl": "Y", "ntnum": "4331659999", "typ": "C", "rsn": "", "items": [{"sgst": 49.17, "rt": 18, "num": 1, "txval": 546.29, "cgst": 49.17}]}, {"dt": "07-08-2020", "val": 1289.24, "diffprcnt": 1, "itcavl": "Y", "ntnum": "4331660010", "typ": "C", "rsn": "", "items": [{"sgst": 98.33, "rt": 18, "num": 1, "txval": 1092.58, "cgst": 98.33}]}, {"dt": "21-08-2020", "val": 3626.27, "diffprcnt": 1, "itcavl": "Y", "ntnum": "4331661702", "typ": "C", "rsn": "", "items": [{"sgst": 276.58, "rt": 18, "num": 1, "txval": 3073.11, "cgst": 276.58}]}], "ctin": "33AAACH1004N1Z1"}]}