{"b2b": [{"inv": [{"dt": "23-11-2022", "val": 28320, "rev": "N", "itcavl": "Y", "diffprcnt": 1, "pos": "33", "typ": "R", "inum": "116/2023", "rsn": "", "items": [{"sgst": 2160, "rt": 18, "num": 1800, "txval": 24000, "cgst": 2160}]}], "trdnm": "THAAI CHETTINAD RESTAURANT", "supfildt": "09-12-2022", "supprd": "112022", "ctin": "33AACFT5369D1ZA"}, {"inv": [{"dt": "07-11-2022", "val": 2700, "rev": "N", "itcavl": "Y", "diffprcnt": 1, "pos": "33", "typ": "R", "inum": "44926", "rsn": "", "items": [{"sgst": 144.65, "rt": 12, "num": 1, "txval": 2410.8, "cgst": 144.65, "cess": 0}]}, {"dt": "07-11-2022", "val": 1411, "rev": "N", "itcavl": "Y", "diffprcnt": 1, "pos": "33", "typ": "R", "inum": "44985", "rsn": "", "items": [{"sgst": 75.6, "rt": 12, "num": 1, "txval": 1260, "cgst": 75.6, "cess": 0}]}], "trdnm": "SARASWATHI AGENCIES", "supfildt": "05-12-2022", "supprd": "112022", "ctin": "33AEEPR4761D2ZM"}, {"inv": [{"dt": "30-11-2022", "val": 12.01, "rev": "N", "itcavl": "Y", "diffprcnt": 1, "pos": "33", "typ": "R", "inum": "M221130002344728", "rsn": "", "items": [{"sgst": 0.92, "rt": 18, "num": 1, "txval": 10.17, "cgst": 0.92, "cess": 0, "igst": 0}]}], "trdnm": "BANK OF BARODA", "supfildt": "09-12-2022", "supprd": "112022", "ctin": "33AAACB1534F3ZB"}, {"inv": [{"val": 1408.92, "rev": "N", "itcavl": "Y", "diffprcnt": 1, "irn": "595d83d539dfcf2436149d2f6d508413745a93a246d173b644885c2b10f7cace", "typ": "R", "irngendate": "01-11-2022", "inum": "C33E222300100582", "rsn": "", "dt": "01-11-2022", "pos": "33", "srctyp": "E-Invoice", "items": [{"sgst": 107.46, "rt": 18, "num": 1, "txval": 1194, "cgst": 107.46, "cess": 0, "igst": 0}]}], "trdnm": "RELIANCE JIO INFOCOMM LIMITED", "supfildt": "09-12-2022", "supprd": "112022", "ctin": "33AABCI6363G1ZQ"}, {"inv": [{"dt": "30-11-2022", "val": 1591.82, "rev": "N", "itcavl": "Y", "diffprcnt": 1, "pos": "33", "typ": "R", "inum": "3301112200796553", "rsn": "", "items": [{"sgst": 121.41, "rt": 18, "num": 1, "txval": 1349, "cgst": 121.41}]}], "trdnm": "KARUR VYSYA BANK LTD", "supfildt": "09-12-2022", "supprd": "112022", "ctin": "33AAACT3373J1ZD"}, {"inv": [{"dt": "02-11-2022", "val": 16242.59, "rev": "N", "itcavl": "Y", "diffprcnt": 1, "pos": "33", "typ": "R", "inum": "9233197784", "rsn": "", "items": [{"sgst": 870.14, "rt": 12, "num": 1, "txval": 14502.31, "cgst": 870.14, "cess": 0}]}, {"dt": "02-11-2022", "val": 108115.38, "rev": "N", "itcavl": "Y", "diffprcnt": 1, "pos": "33", "typ": "R", "inum": "9233197785", "rsn": "", "items": [{"sgst": 8246.08, "rt": 18, "num": 1, "txval": 91623.22, "cgst": 8246.08, "cess": 0}]}, {"dt": "02-11-2022", "val": 794040.12, "rev": "N", "itcavl": "Y", "diffprcnt": 1, "pos": "33", "typ": "R", "inum": "9233197786", "rsn": "", "items": [{"sgst": 60562.37, "rt": 18, "num": 1, "txval": 672915.38, "cgst": 60562.37, "cess": 0}]}, {"dt": "02-11-2022", "val": 385859.68, "rev": "N", "itcavl": "Y", "diffprcnt": 1, "pos": "33", "typ": "R", "inum": "9233197787", "rsn": "", "items": [{"sgst": 29429.97, "rt": 18, "num": 1, "txval": 326999.74, "cgst": 29429.97, "cess": 0}]}, {"dt": "02-11-2022", "val": 279399.08, "rev": "N", "itcavl": "Y", "diffprcnt": 1, "pos": "33", "typ": "R", "inum": "9233197788", "rsn": "", "items": [{"sgst": 0, "rt": 0, "num": 1, "txval": 0, "cgst": 0, "cess": 0}, {"sgst": 4909.07, "rt": 5, "num": 2, "txval": 196363.16, "cgst": 4909.07, "cess": 0}, {"sgst": 1269.29, "rt": 12, "num": 3, "txval": 21154.69, "cgst": 1269.29, "cess": 0}, {"sgst": 3777.29, "rt": 18, "num": 4, "txval": 41969.93, "cgst": 3777.29, "cess": 0}]}, {"dt": "04-11-2022", "val": 30913.22, "rev": "N", "itcavl": "Y", "diffprcnt": 1, "pos": "33", "typ": "R", "inum": "9233200286", "rsn": "", "items": [{"sgst": 2357.79, "rt": 18, "num": 1, "txval": 26197.64, "cgst": 2357.79, "cess": 0}]}, {"dt": "04-11-2022", "val": 347272.9, "rev": "N", "itcavl": "Y", "diffprcnt": 1, "pos": "33", "typ": "R", "inum": "9233200287", "rsn": "", "items": [{"sgst": 166.02, "rt": 12, "num": 1, "txval": 2767.04, "cgst": 166.02, "cess": 0}, {"sgst": 26250.51, "rt": 18, "num": 2, "txval": 291672.8, "cgst": 26250.51, "cess": 0}]}, {"dt": "04-11-2022", "val": 263209.19, "rev": "N", "itcavl": "Y", "diffprcnt": 1, "pos": "33", "typ": "R", "inum": "9233200288", "rsn": "", "items": [{"sgst": 533.24, "rt": 5, "num": 1, "txval": 21329.8, "cgst": 533.24, "cess": 0}, {"sgst": 872.14, "rt": 12, "num": 2, "txval": 14535.62, "cgst": 872.14, "cess": 0}, {"sgst": 17125.4, "rt": 18, "num": 3, "txval": 190282.21, "cgst": 17125.4, "cess": 0}]}, {"dt": "04-11-2022", "val": 269567.23, "rev": "N", "itcavl": "Y", "diffprcnt": 1, "pos": "33", "typ": "R", "inum": "9233200289", "rsn": "", "items": [{"sgst": 20560.22, "rt": 18, "num": 1, "txval": 228446.79, "cgst": 20560.22, "cess": 0}]}, {"dt": "07-11-2022", "val": 98763.2, "rev": "N", "itcavl": "Y", "diffprcnt": 1, "pos": "33", "typ": "R", "inum": "9233201914", "rsn": "", "items": [{"sgst": 2863.28, "rt": 12, "num": 1, "txval": 47721.31, "cgst": 2863.28, "cess": 0}, {"sgst": 3456.25, "rt": 18, "num": 2, "txval": 38402.83, "cgst": 3456.25, "cess": 0}]}, {"dt": "07-11-2022", "val": 1022055.17, "rev": "N", "itcavl": "Y", "diffprcnt": 1, "pos": "33", "typ": "R", "inum": "9233201915", "rsn": "", "items": [{"sgst": 77953.32, "rt": 18, "num": 1, "txval": 866148.53, "cgst": 77953.32, "cess": 0}]}, {"dt": "07-11-2022", "val": 577905.4, "rev": "N", "itcavl": "Y", "diffprcnt": 1, "pos": "33", "typ": "R", "inum": "9233201916", "rsn": "", "items": [{"sgst": 6037.89, "rt": 5, "num": 1, "txval": 241516.94, "cgst": 6037.89, "cess": 0}, {"sgst": 2275.12, "rt": 12, "num": 2, "txval": 37918.59, "cgst": 2275.12, "cess": 0}, {"sgst": 21496.57, "rt": 18, "num": 3, "txval": 238850.71, "cgst": 21496.57, "cess": 0}]}, {"dt": "07-11-2022", "val": 282499.32, "rev": "N", "itcavl": "Y", "diffprcnt": 1, "pos": "33", "typ": "R", "inum": "9233201917", "rsn": "", "items": [{"sgst": 21546.55, "rt": 18, "num": 1, "txval": 239406.22, "cgst": 21546.55, "cess": 0}]}, {"dt": "07-11-2022", "val": 119073.23, "rev": "N", "itcavl": "Y", "diffprcnt": 1, "pos": "33", "typ": "R", "inum": "9233201918", "rsn": "", "items": [{"sgst": 9081.86, "rt": 18, "num": 1, "txval": 100909.51, "cgst": 9081.86, "cess": 0}]}, {"dt": "07-11-2022", "val": 66194.16, "rev": "N", "itcavl": "Y", "diffprcnt": 1, "pos": "33", "typ": "R", "inum": "9233202028", "rsn": "", "items": [{"sgst": 5048.71, "rt": 18, "num": 1, "txval": 56096.74, "cgst": 5048.71, "cess": 0}]}, {"dt": "07-11-2022", "val": 872597.87, "rev": "N", "itcavl": "Y", "diffprcnt": 1, "pos": "33", "typ": "R", "inum": "9233202030", "rsn": "", "items": [{"sgst": 66554.07, "rt": 18, "num": 1, "txval": 739489.73, "cgst": 66554.07, "cess": 0}]}, {"dt": "09-11-2022", "val": 10279.77, "rev": "N", "itcavl": "Y", "diffprcnt": 1, "pos": "33", "typ": "R", "inum": "9233204437", "rsn": "", "items": [{"sgst": 550.7, "rt": 12, "num": 1, "txval": 9178.37, "cgst": 550.7, "cess": 0}]}, {"dt": "09-11-2022", "val": 251542.42, "rev": "N", "itcavl": "Y", "diffprcnt": 1, "pos": "33", "typ": "R", "inum": "9233204438", "rsn": "", "items": [{"sgst": 4436.96, "rt": 5, "num": 1, "txval": 177478, "cgst": 4436.96, "cess": 0}, {"sgst": 389.25, "rt": 12, "num": 2, "txval": 6487.44, "cgst": 389.25, "cess": 0}, {"sgst": 4417.98, "rt": 18, "num": 3, "txval": 49088.6, "cgst": 4417.98, "cess": 0}, {"sgst": 0, "rt": 0, "num": 4, "txval": 0, "cgst": 0, "cess": 0}]}, {"dt": "09-11-2022", "val": 354758.88, "rev": "N", "itcavl": "Y", "diffprcnt": 1, "pos": "33", "typ": "R", "inum": "9233204439", "rsn": "", "items": [{"sgst": 27057.86, "rt": 18, "num": 1, "txval": 300643.16, "cgst": 27057.86, "cess": 0}]}, {"dt": "09-11-2022", "val": 280988.92, "rev": "N", "itcavl": "Y", "diffprcnt": 1, "pos": "33", "typ": "R", "inum": "9233204440", "rsn": "", "items": [{"sgst": 21431.36, "rt": 18, "num": 1, "txval": 238126.2, "cgst": 21431.36, "cess": 0}]}, {"dt": "09-11-2022", "val": 62612.03, "rev": "N", "itcavl": "Y", "diffprcnt": 1, "pos": "33", "typ": "R", "inum": "9233204448", "rsn": "", "items": [{"sgst": 2232.89, "rt": 18, "num": 1, "txval": 24809.93, "cgst": 2232.89, "cess": 0}, {"sgst": 1785.88, "rt": 12, "num": 2, "txval": 29764.56, "cgst": 1785.88, "cess": 0}]}, {"dt": "10-11-2022", "val": 902824.35, "rev": "N", "itcavl": "Y", "diffprcnt": 1, "pos": "33", "typ": "R", "inum": "9233205260", "rsn": "", "items": [{"sgst": 68859.49, "rt": 18, "num": 1, "txval": 765105.37, "cgst": 68859.49, "cess": 0}]}, {"dt": "12-11-2022", "val": 62411.49, "rev": "N", "itcavl": "Y", "diffprcnt": 1, "pos": "33", "typ": "R", "inum": "9233206791", "rsn": "", "items": [{"sgst": 3481.28, "rt": 18, "num": 1, "txval": 38680.98, "cgst": 3481.28, "cess": 0}, {"sgst": 898.28, "rt": 12, "num": 2, "txval": 14971.39, "cgst": 898.28, "cess": 0}]}, {"dt": "12-11-2022", "val": 202799.93, "rev": "N", "itcavl": "Y", "diffprcnt": 1, "pos": "33", "typ": "R", "inum": "9233206795", "rsn": "", "items": [{"sgst": 442.73, "rt": 12, "num": 1, "txval": 7378.75, "cgst": 442.73, "cess": 0}, {"sgst": 0, "rt": 0, "num": 2, "txval": 0, "cgst": 0, "cess": 0}, {"sgst": 14837.45, "rt": 18, "num": 3, "txval": 164860.82, "cgst": 14837.45, "cess": 0}]}, {"dt": "12-11-2022", "val": 251349.9, "rev": "N", "itcavl": "Y", "diffprcnt": 1, "pos": "33", "typ": "R", "inum": "9233206796", "rsn": "", "items": [{"sgst": 5217.15, "rt": 5, "num": 1, "txval": 208685.85, "cgst": 5217.15, "cess": 0}, {"sgst": 851.88, "rt": 18, "num": 2, "txval": 9465.32, "cgst": 851.88, "cess": 0}, {"sgst": 1128.25, "rt": 12, "num": 3, "txval": 18804.17, "cgst": 1128.25, "cess": 0}]}, {"dt": "12-11-2022", "val": 3053.7, "rev": "N", "itcavl": "Y", "diffprcnt": 1, "pos": "33", "typ": "R", "inum": "9233206797", "rsn": "", "items": [{"sgst": 232.91, "rt": 18, "num": 1, "txval": 2587.88, "cgst": 232.91, "cess": 0}]}, {"dt": "12-11-2022", "val": 293538.49, "rev": "N", "itcavl": "Y", "diffprcnt": 1, "pos": "33", "typ": "R", "inum": "9233206807", "rsn": "", "items": [{"sgst": 22388.51, "rt": 18, "num": 1, "txval": 248761.47, "cgst": 22388.51, "cess": 0}]}, {"dt": "12-11-2022", "val": 195500.71, "rev": "N", "itcavl": "Y", "diffprcnt": 1, "pos": "33", "typ": "R", "inum": "9233206808", "rsn": "", "items": [{"sgst": 14911.09, "rt": 18, "num": 1, "txval": 165678.53, "cgst": 14911.09, "cess": 0}]}, {"dt": "14-11-2022", "val": 43277.45, "rev": "N", "itcavl": "Y", "diffprcnt": 1, "pos": "33", "typ": "R", "inum": "9233208185", "rsn": "", "items": [{"sgst": 2118.97, "rt": 18, "num": 1, "txval": 23544.12, "cgst": 2118.97, "cess": 0}, {"sgst": 830.11, "rt": 12, "num": 2, "txval": 13835.17, "cgst": 830.11, "cess": 0}]}, {"dt": "14-11-2022", "val": 930445.89, "rev": "N", "itcavl": "Y", "diffprcnt": 1, "pos": "33", "typ": "R", "inum": "9233208186", "rsn": "", "items": [{"sgst": 525.73, "rt": 12, "num": 1, "txval": 8762.28, "cgst": 525.73, "cess": 0}, {"sgst": 70217.66, "rt": 18, "num": 2, "txval": 780196.83, "cgst": 70217.66, "cess": 0}]}, {"dt": "14-11-2022", "val": 725404.22, "rev": "N", "itcavl": "Y", "diffprcnt": 1, "pos": "33", "typ": "R", "inum": "9233208187", "rsn": "", "items": [{"sgst": 28289.8, "rt": 18, "num": 1, "txval": 314331.15, "cgst": 28289.8, "cess": 0}, {"sgst": 7314.56, "rt": 5, "num": 2, "txval": 292583.15, "cgst": 7314.56, "cess": 0}, {"sgst": 2532.92, "rt": 12, "num": 3, "txval": 42215.36, "cgst": 2532.92, "cess": 0}]}, {"dt": "14-11-2022", "val": 344851.58, "rev": "N", "itcavl": "Y", "diffprcnt": 1, "pos": "33", "typ": "R", "inum": "9233208188", "rsn": "", "items": [{"sgst": 26302.24, "rt": 18, "num": 1, "txval": 292247.1, "cgst": 26302.24, "cess": 0}]}, {"dt": "14-11-2022", "val": 109332.79, "rev": "N", "itcavl": "Y", "diffprcnt": 1, "pos": "33", "typ": "R", "inum": "9233208189", "rsn": "", "items": [{"sgst": 8338.94, "rt": 18, "num": 1, "txval": 92654.91, "cgst": 8338.94, "cess": 0}]}, {"dt": "14-11-2022", "val": 426617.09, "rev": "N", "itcavl": "Y", "diffprcnt": 1, "pos": "33", "typ": "R", "inum": "9233208190", "rsn": "", "items": [{"sgst": 10157.55, "rt": 5, "num": 1, "txval": 406301.99, "cgst": 10157.55, "cess": 0}]}, {"dt": "14-11-2022", "val": 1008272.67, "rev": "N", "itcavl": "Y", "diffprcnt": 1, "pos": "33", "typ": "R", "inum": "9233208582", "rsn": "", "items": [{"sgst": 76902.14, "rt": 18, "num": 1, "txval": 854468.39, "cgst": 76902.14, "cess": 0}]}, {"dt": "16-11-2022", "val": 64838.33, "rev": "N", "itcavl": "Y", "diffprcnt": 1, "pos": "33", "typ": "R", "inum": "9233210658", "rsn": "", "items": [{"sgst": 2050.61, "rt": 18, "num": 1, "txval": 22784.63, "cgst": 2050.61, "cess": 0}, {"sgst": 2033.17, "rt": 12, "num": 2, "txval": 33886.14, "cgst": 2033.17, "cess": 0}]}, {"dt": "16-11-2022", "val": 630944.63, "rev": "N", "itcavl": "Y", "diffprcnt": 1, "pos": "33", "typ": "R", "inum": "9233210659", "rsn": "", "items": [{"sgst": 48122.85, "rt": 18, "num": 1, "txval": 534698.93, "cgst": 48122.85, "cess": 0}]}, {"dt": "16-11-2022", "val": 523629.56, "rev": "N", "itcavl": "Y", "diffprcnt": 1, "pos": "33", "typ": "R", "inum": "9233210660", "rsn": "", "items": [{"sgst": 1515.79, "rt": 12, "num": 1, "txval": 25263.37, "cgst": 1515.79, "cess": 0}, {"sgst": 10347.12, "rt": 18, "num": 2, "txval": 114968.16, "cgst": 10347.12, "cess": 0}, {"sgst": 8563.61, "rt": 5, "num": 3, "txval": 342544.99, "cgst": 8563.61, "cess": 0}]}, {"dt": "16-11-2022", "val": 386325.27, "rev": "N", "itcavl": "Y", "diffprcnt": 1, "pos": "33", "typ": "R", "inum": "9233210661", "rsn": "", "items": [{"sgst": 29465.49, "rt": 18, "num": 1, "txval": 327394.29, "cgst": 29465.49, "cess": 0}]}, {"dt": "16-11-2022", "val": 10008.13, "rev": "N", "itcavl": "Y", "diffprcnt": 1, "pos": "33", "typ": "R", "inum": "9233210662", "rsn": "", "items": [{"sgst": 238.29, "rt": 5, "num": 1, "txval": 9531.55, "cgst": 238.29, "cess": 0}]}, {"dt": "16-11-2022", "val": 24984.84, "rev": "N", "itcavl": "Y", "diffprcnt": 1, "pos": "33", "typ": "R", "inum": "9233210883", "rsn": "", "items": [{"sgst": 1905.62, "rt": 18, "num": 1, "txval": 21173.6, "cgst": 1905.62, "cess": 0}]}, {"dt": "17-11-2022", "val": 833005.53, "rev": "N", "itcavl": "Y", "diffprcnt": 1, "pos": "33", "typ": "R", "inum": "9233211886", "rsn": "", "items": [{"sgst": 63534.29, "rt": 18, "num": 1, "txval": 705936.95, "cgst": 63534.29, "cess": 0}]}, {"dt": "17-11-2022", "val": 21100.24, "rev": "N", "itcavl": "Y", "diffprcnt": 1, "pos": "33", "typ": "R", "inum": "9233212049", "rsn": "", "items": [{"sgst": 1609.34, "rt": 18, "num": 1, "txval": 17881.56, "cgst": 1609.34, "cess": 0}]}, {"dt": "18-11-2022", "val": 9281.02, "rev": "N", "itcavl": "Y", "diffprcnt": 1, "pos": "33", "typ": "R", "inum": "9233213013", "rsn": "", "items": [{"sgst": 497.2, "rt": 12, "num": 1, "txval": 8286.62, "cgst": 497.2, "cess": 0}]}, {"dt": "18-11-2022", "val": 86147.71, "rev": "N", "itcavl": "Y", "diffprcnt": 1, "pos": "33", "typ": "R", "inum": "9233213014", "rsn": "", "items": [{"sgst": 1582.69, "rt": 12, "num": 1, "txval": 26378.17, "cgst": 1582.69, "cess": 0}, {"sgst": 4317.27, "rt": 18, "num": 2, "txval": 47969.62, "cgst": 4317.27, "cess": 0}]}, {"dt": "18-11-2022", "val": 386834.18, "rev": "N", "itcavl": "Y", "diffprcnt": 1, "pos": "33", "typ": "R", "inum": "9233213015", "rsn": "", "items": [{"sgst": 29504.29, "rt": 18, "num": 1, "txval": 327825.6, "cgst": 29504.29, "cess": 0}]}, {"dt": "18-11-2022", "val": 707442.23, "rev": "N", "itcavl": "Y", "diffprcnt": 1, "pos": "33", "typ": "R", "inum": "9233213016", "rsn": "", "items": [{"sgst": 53957.44, "rt": 18, "num": 1, "txval": 599527.35, "cgst": 53957.44, "cess": 0}]}, {"dt": "18-11-2022", "val": 359121.4, "rev": "N", "itcavl": "Y", "diffprcnt": 1, "pos": "33", "typ": "R", "inum": "9233213017", "rsn": "", "items": [{"sgst": 1269.96, "rt": 5, "num": 1, "txval": 50798.63, "cgst": 1269.96, "cess": 0}, {"sgst": 20590.87, "rt": 18, "num": 2, "txval": 228787.44, "cgst": 20590.87, "cess": 0}, {"sgst": 1918.59, "rt": 12, "num": 3, "txval": 31976.49, "cgst": 1918.59, "cess": 0}]}, {"dt": "18-11-2022", "val": 3159.1, "rev": "N", "itcavl": "Y", "diffprcnt": 1, "pos": "33", "typ": "R", "inum": "9233213018", "rsn": "", "items": [{"sgst": 169.24, "rt": 12, "num": 1, "txval": 2820.62, "cgst": 169.24, "cess": 0}]}, {"dt": "21-11-2022", "val": 73748.08, "rev": "N", "itcavl": "Y", "diffprcnt": 1, "pos": "33", "typ": "R", "inum": "9233215354", "rsn": "", "items": [{"sgst": 4442.99, "rt": 18, "num": 1, "txval": 49366.71, "cgst": 4442.99, "cess": 0}, {"sgst": 830.11, "rt": 12, "num": 2, "txval": 13835.17, "cgst": 830.11, "cess": 0}]}, {"dt": "21-11-2022", "val": 335620.29, "rev": "N", "itcavl": "Y", "diffprcnt": 1, "pos": "33", "typ": "R", "inum": "9233215358", "rsn": "", "items": [{"sgst": 5672.97, "rt": 5, "num": 1, "txval": 226918.71, "cgst": 5672.97, "cess": 0}, {"sgst": 4195.12, "rt": 18, "num": 2, "txval": 46612.43, "cgst": 4195.12, "cess": 0}, {"sgst": 2268.9, "rt": 12, "num": 3, "txval": 37815.17, "cgst": 2268.9, "cess": 0}]}, {"dt": "21-11-2022", "val": 226684.45, "rev": "N", "itcavl": "Y", "diffprcnt": 1, "pos": "33", "typ": "R", "inum": "9233215359", "rsn": "", "items": [{"sgst": 17289.49, "rt": 18, "num": 1, "txval": 192105.47, "cgst": 17289.49, "cess": 0}]}, {"dt": "21-11-2022", "val": 634147.64, "rev": "N", "itcavl": "Y", "diffprcnt": 1, "pos": "33", "typ": "R", "inum": "9233215360", "rsn": "", "items": [{"sgst": 608.75, "rt": 12, "num": 1, "txval": 10145.79, "cgst": 608.75, "cess": 0}, {"sgst": 0, "rt": 0, "num": 2, "txval": 0, "cgst": 0, "cess": 0}, {"sgst": 47500.48, "rt": 18, "num": 3, "txval": 527783.39, "cgst": 47500.48, "cess": 0}]}, {"dt": "21-11-2022", "val": 872264.48, "rev": "N", "itcavl": "Y", "diffprcnt": 1, "pos": "33", "typ": "R", "inum": "9233215603", "rsn": "", "items": [{"sgst": 66528.62, "rt": 18, "num": 1, "txval": 739207.24, "cgst": 66528.62, "cess": 0}]}, {"dt": "23-11-2022", "val": 9281.02, "rev": "N", "itcavl": "Y", "diffprcnt": 1, "pos": "33", "typ": "R", "inum": "9233216905", "rsn": "", "items": [{"sgst": 497.2, "rt": 12, "num": 1, "txval": 8286.62, "cgst": 497.2, "cess": 0}]}, {"dt": "23-11-2022", "val": 172640.67, "rev": "N", "itcavl": "Y", "diffprcnt": 1, "pos": "33", "typ": "R", "inum": "9233216906", "rsn": "", "items": [{"sgst": 6836.53, "rt": 18, "num": 1, "txval": 75961.52, "cgst": 6836.53, "cess": 0}, {"sgst": 4446.76, "rt": 12, "num": 2, "txval": 74112.57, "cgst": 4446.76, "cess": 0}]}, {"dt": "23-11-2022", "val": 1095575.27, "rev": "N", "itcavl": "Y", "diffprcnt": 1, "pos": "33", "typ": "R", "inum": "9233216907", "rsn": "", "items": [{"sgst": 83560.78, "rt": 18, "num": 1, "txval": 928453.71, "cgst": 83560.78, "cess": 0}]}, {"dt": "23-11-2022", "val": 513268.85, "rev": "N", "itcavl": "Y", "diffprcnt": 1, "pos": "33", "typ": "R", "inum": "9233216908", "rsn": "", "items": [{"sgst": 39147.63, "rt": 18, "num": 1, "txval": 434973.59, "cgst": 39147.63, "cess": 0}]}, {"dt": "23-11-2022", "val": 744243.39, "rev": "N", "itcavl": "Y", "diffprcnt": 1, "pos": "33", "typ": "R", "inum": "9233216909", "rsn": "", "items": [{"sgst": 10889.69, "rt": 5, "num": 1, "txval": 435588.03, "cgst": 10889.69, "cess": 0}, {"sgst": 17989.04, "rt": 18, "num": 2, "txval": 199878.4, "cgst": 17989.04, "cess": 0}, {"sgst": 2733.19, "rt": 12, "num": 3, "txval": 45553.12, "cgst": 2733.19, "cess": 0}]}, {"dt": "24-11-2022", "val": 959085.72, "rev": "N", "itcavl": "Y", "diffprcnt": 1, "pos": "33", "typ": "R", "inum": "9233218253", "rsn": "", "items": [{"sgst": 73150.61, "rt": 18, "num": 1, "txval": 812784.5, "cgst": 73150.61, "cess": 0}]}, {"dt": "24-11-2022", "val": 2896.61, "rev": "N", "itcavl": "Y", "diffprcnt": 1, "pos": "33", "typ": "R", "inum": "9233218254", "rsn": "", "items": [{"sgst": 220.93, "rt": 18, "num": 1, "txval": 2454.75, "cgst": 220.93, "cess": 0}]}, {"dt": "25-11-2022", "val": 20583.94, "rev": "N", "itcavl": "Y", "diffprcnt": 1, "pos": "33", "typ": "R", "inum": "9233219417", "rsn": "", "items": [{"sgst": 718.63, "rt": 12, "num": 1, "txval": 11977.12, "cgst": 718.63, "cess": 0}, {"sgst": 546.83, "rt": 18, "num": 2, "txval": 6075.9, "cgst": 546.83, "cess": 0}]}, {"dt": "25-11-2022", "val": 404405.29, "rev": "N", "itcavl": "Y", "diffprcnt": 1, "pos": "33", "typ": "R", "inum": "9233219421", "rsn": "", "items": [{"sgst": 30844.44, "rt": 18, "num": 1, "txval": 342716.41, "cgst": 30844.44, "cess": 0}]}, {"dt": "25-11-2022", "val": 218583.7, "rev": "N", "itcavl": "Y", "diffprcnt": 1, "pos": "33", "typ": "R", "inum": "9233219422", "rsn": "", "items": [{"sgst": 16671.65, "rt": 18, "num": 1, "txval": 185240.4, "cgst": 16671.65, "cess": 0}]}, {"dt": "25-11-2022", "val": 431678.18, "rev": "N", "itcavl": "Y", "diffprcnt": 1, "pos": "33", "typ": "R", "inum": "9233219423", "rsn": "", "items": [{"sgst": 7204.2, "rt": 5, "num": 1, "txval": 288168.38, "cgst": 7204.2, "cess": 0}, {"sgst": 1615.08, "rt": 12, "num": 2, "txval": 26918.15, "cgst": 1615.08, "cess": 0}, {"sgst": 7547.27, "rt": 18, "num": 3, "txval": 83858.55, "cgst": 7547.27, "cess": 0}]}, {"dt": "25-11-2022", "val": 3745.79, "rev": "N", "itcavl": "Y", "diffprcnt": 1, "pos": "33", "typ": "R", "inum": "9233219424", "rsn": "", "items": [{"sgst": 285.7, "rt": 18, "num": 1, "txval": 3174.39, "cgst": 285.7, "cess": 0}]}, {"dt": "28-11-2022", "val": 15235.33, "rev": "N", "itcavl": "Y", "diffprcnt": 1, "pos": "33", "typ": "R", "inum": "9233221556", "rsn": "", "items": [{"sgst": 1162.02, "rt": 18, "num": 1, "txval": 12911.29, "cgst": 1162.02, "cess": 0}]}, {"dt": "28-11-2022", "val": 598169.07, "rev": "N", "itcavl": "Y", "diffprcnt": 1, "pos": "33", "typ": "R", "inum": "9233221560", "rsn": "", "items": [{"sgst": 45623.06, "rt": 18, "num": 1, "txval": 506922.95, "cgst": 45623.06, "cess": 0}]}, {"dt": "28-11-2022", "val": 310513.8, "rev": "N", "itcavl": "Y", "diffprcnt": 1, "pos": "33", "typ": "R", "inum": "9233221561", "rsn": "", "items": [{"sgst": 5847.38, "rt": 5, "num": 1, "txval": 233895.08, "cgst": 5847.38, "cess": 0}, {"sgst": 2492.54, "rt": 18, "num": 2, "txval": 27695.01, "cgst": 2492.54, "cess": 0}, {"sgst": 1727.35, "rt": 12, "num": 3, "txval": 28789.17, "cgst": 1727.35, "cess": 0}]}, {"dt": "28-11-2022", "val": 151168.9, "rev": "N", "itcavl": "Y", "diffprcnt": 1, "pos": "33", "typ": "R", "inum": "9233221562", "rsn": "", "items": [{"sgst": 11529.83, "rt": 18, "num": 1, "txval": 128109.24, "cgst": 11529.83, "cess": 0}]}, {"dt": "28-11-2022", "val": 170710.49, "rev": "N", "itcavl": "Y", "diffprcnt": 1, "pos": "33", "typ": "R", "inum": "9233221563", "rsn": "", "items": [{"sgst": 13020.29, "rt": 18, "num": 1, "txval": 144669.91, "cgst": 13020.29, "cess": 0}]}, {"dt": "29-11-2022", "val": 6786.02, "rev": "N", "itcavl": "Y", "diffprcnt": 1, "pos": "33", "typ": "R", "inum": "9233222733", "rsn": "", "items": [{"sgst": 517.58, "rt": 18, "num": 1, "txval": 5750.86, "cgst": 517.58, "cess": 0}]}, {"dt": "30-11-2022", "val": 31411.62, "rev": "N", "itcavl": "Y", "diffprcnt": 1, "pos": "33", "typ": "R", "inum": "9233224052", "rsn": "", "items": [{"sgst": 1177.79, "rt": 18, "num": 1, "txval": 13086.55, "cgst": 1177.79, "cess": 0}, {"sgst": 855.51, "rt": 12, "num": 2, "txval": 14258.47, "cgst": 855.51, "cess": 0}]}, {"dt": "30-11-2022", "val": 379517.05, "rev": "N", "itcavl": "Y", "diffprcnt": 1, "pos": "33", "typ": "R", "inum": "9233224056", "rsn": "", "items": [{"sgst": 28946.17, "rt": 18, "num": 1, "txval": 321624.71, "cgst": 28946.17, "cess": 0}]}, {"dt": "30-11-2022", "val": 349999.81, "rev": "N", "itcavl": "Y", "diffprcnt": 1, "pos": "33", "typ": "R", "inum": "9233224057", "rsn": "", "items": [{"sgst": 26694.91, "rt": 18, "num": 1, "txval": 296609.99, "cgst": 26694.91, "cess": 0}]}, {"dt": "30-11-2022", "val": 220229.46, "rev": "N", "itcavl": "Y", "diffprcnt": 1, "pos": "33", "typ": "R", "inum": "9233224058", "rsn": "", "items": [{"sgst": 1683.92, "rt": 12, "num": 1, "txval": 28065.24, "cgst": 1683.92, "cess": 0}, {"sgst": 4350.48, "rt": 18, "num": 2, "txval": 48338.53, "cgst": 4350.48, "cess": 0}, {"sgst": 3137.05, "rt": 5, "num": 3, "txval": 125482.79, "cgst": 3137.05, "cess": 0}]}, {"dt": "30-11-2022", "val": 45625.9, "rev": "N", "itcavl": "Y", "diffprcnt": 1, "pos": "33", "typ": "R", "inum": "9233224059", "rsn": "", "items": [{"sgst": 3479.94, "rt": 18, "num": 1, "txval": 38666.02, "cgst": 3479.94, "cess": 0}]}], "trdnm": "HINDUSTAN UNILEVER LIMITED", "supfildt": "11-12-2022", "supprd": "112022", "ctin": "33AAACH1004N1Z1"}, {"inv": [{"dt": "09-11-2022", "val": 6340, "rev": "N", "itcavl": "Y", "diffprcnt": 1, "pos": "33", "typ": "R", "inum": "6840", "rsn": "", "items": [{"sgst": 311.55, "rt": 18, "num": 1, "txval": 3461.88, "cgst": 311.55, "cess": 0}, {"sgst": 242.27, "rt": 28, "num": 2, "txval": 1730.47, "cgst": 242.27, "cess": 0}, {"sgst": 2.14, "rt": 12, "num": 3, "txval": 35.72, "cgst": 2.14, "cess": 0}]}], "trdnm": "AKILANDESWARI AUTOMOBILES", "supfildt": "09-12-2022", "supprd": "112022", "ctin": "33AWOPM5134D1ZO"}], "cdnr": [{"trdnm": "HINDUSTAN UNILEVER LIMITED", "supfildt": "11-12-2022", "supprd": "112022", "nt": [{"dt": "12-11-2022", "val": 11129.88, "diffprcnt": 1, "itcavl": "Y", "rev": "N", "ntnum": "4331957338", "pos": "33", "typ": "C", "rsn": "", "items": [{"sgst": 848.89, "rt": 18, "num": 1, "txval": 9432.1, "cgst": 848.89, "cess": 0}], "suptyp": "R"}, {"dt": "12-11-2022", "val": 8766.12, "diffprcnt": 1, "itcavl": "Y", "rev": "N", "ntnum": "4331957339", "pos": "33", "typ": "C", "rsn": "", "items": [{"sgst": 668.6, "rt": 18, "num": 1, "txval": 7428.92, "cgst": 668.6, "cess": 0}], "suptyp": "R"}, {"dt": "12-11-2022", "val": 4738.66, "diffprcnt": 1, "itcavl": "Y", "rev": "N", "ntnum": "4331957340", "pos": "33", "typ": "C", "rsn": "", "items": [{"sgst": 253.86, "rt": 12, "num": 1, "txval": 4230.94, "cgst": 253.86, "cess": 0}], "suptyp": "R"}, {"dt": "12-11-2022", "val": 6361.8, "diffprcnt": 1, "itcavl": "Y", "rev": "N", "ntnum": "4331957341", "pos": "33", "typ": "C", "rsn": "", "items": [{"sgst": 485.22, "rt": 18, "num": 1, "txval": 5391.36, "cgst": 485.22, "cess": 0}], "suptyp": "R"}, {"dt": "12-11-2022", "val": 1506.76, "diffprcnt": 1, "itcavl": "Y", "rev": "N", "ntnum": "4331957342", "pos": "33", "typ": "C", "rsn": "", "items": [{"sgst": 114.92, "rt": 18, "num": 1, "txval": 1276.92, "cgst": 114.92, "cess": 0}], "suptyp": "R"}, {"dt": "12-11-2022", "val": 8467.12, "diffprcnt": 1, "itcavl": "Y", "rev": "N", "ntnum": "4331957343", "pos": "33", "typ": "C", "rsn": "", "items": [{"sgst": 645.79, "rt": 18, "num": 1, "txval": 7175.54, "cgst": 645.79, "cess": 0}], "suptyp": "R"}, {"dt": "19-11-2022", "val": 5916.55, "diffprcnt": 1, "itcavl": "Y", "rev": "N", "ntnum": "4331963106", "pos": "33", "typ": "C", "rsn": "", "items": [{"sgst": 451.26, "rt": 18, "num": 1, "txval": 5014.03, "cgst": 451.26, "cess": 0}], "suptyp": "R"}, {"dt": "19-11-2022", "val": 3180.93, "diffprcnt": 1, "itcavl": "Y", "rev": "N", "ntnum": "4331963107", "pos": "33", "typ": "C", "rsn": "", "items": [{"sgst": 242.61, "rt": 18, "num": 1, "txval": 2695.71, "cgst": 242.61, "cess": 0}], "suptyp": "R"}, {"dt": "19-11-2022", "val": 3432.62, "diffprcnt": 1, "itcavl": "Y", "rev": "N", "ntnum": "4331963108", "pos": "33", "typ": "C", "rsn": "", "items": [{"sgst": 81.73, "rt": 5, "num": 1, "txval": 3269.16, "cgst": 81.73, "cess": 0}], "suptyp": "R"}, {"dt": "19-11-2022", "val": 15061.76, "diffprcnt": 1, "itcavl": "Y", "rev": "N", "ntnum": "4331963109", "pos": "33", "typ": "C", "rsn": "", "items": [{"sgst": 1148.78, "rt": 18, "num": 1, "txval": 12764.2, "cgst": 1148.78, "cess": 0}], "suptyp": "R"}, {"dt": "19-11-2022", "val": 5916.55, "diffprcnt": 1, "itcavl": "Y", "rev": "N", "ntnum": "4331963110", "pos": "33", "typ": "C", "rsn": "", "items": [{"sgst": 451.26, "rt": 18, "num": 1, "txval": 5014.03, "cgst": 451.26, "cess": 0}], "suptyp": "R"}, {"dt": "19-11-2022", "val": 8133.36, "diffprcnt": 1, "itcavl": "Y", "rev": "N", "ntnum": "4331963111", "pos": "33", "typ": "C", "rsn": "", "items": [{"sgst": 193.65, "rt": 5, "num": 1, "txval": 7746.06, "cgst": 193.65, "cess": 0}], "suptyp": "R"}, {"dt": "19-11-2022", "val": 3053.7, "diffprcnt": 1, "itcavl": "Y", "rev": "N", "ntnum": "4331963112", "pos": "33", "typ": "C", "rsn": "", "items": [{"sgst": 232.91, "rt": 18, "num": 1, "txval": 2587.88, "cgst": 232.91, "cess": 0}], "suptyp": "R"}, {"dt": "19-11-2022", "val": 9181.48, "diffprcnt": 1, "itcavl": "Y", "rev": "N", "ntnum": "4331963113", "pos": "33", "typ": "C", "rsn": "", "items": [{"sgst": 700.28, "rt": 18, "num": 1, "txval": 7780.92, "cgst": 700.28, "cess": 0}], "suptyp": "R"}, {"dt": "19-11-2022", "val": 17377.77, "diffprcnt": 1, "itcavl": "Y", "rev": "N", "ntnum": "4331963114", "pos": "33", "typ": "C", "rsn": "", "items": [{"sgst": 413.76, "rt": 5, "num": 1, "txval": 16550.25, "cgst": 413.76, "cess": 0}], "suptyp": "R"}, {"dt": "19-11-2022", "val": 5196.57, "diffprcnt": 1, "itcavl": "Y", "rev": "N", "ntnum": "4331963115", "pos": "33", "typ": "C", "rsn": "", "items": [{"sgst": 396.35, "rt": 18, "num": 1, "txval": 4403.87, "cgst": 396.35, "cess": 0}], "suptyp": "R"}], "ctin": "33AAACH1004N1Z1"}]}